azstream/__init__.py
azstream/authenticators/__init__.py
azstream/authenticators/auth_status.py
azstream/authenticators/authenticator/__init__.py
azstream/authenticators/authenticator/authenticator.py
azstream/authenticators/bellmedia_authenticator/__init__.py
azstream/authenticators/bellmedia_authenticator/bellmedia_authenticator.py
azstream/authenticators/bellmedia_authenticator/consts.py
azstream/authenticators/bellmedia_authenticator/requests.py
azstream/authenticators/bellmedia_external_authenticator/__init__.py
azstream/authenticators/bellmedia_external_authenticator/bellmedia_external_authenticator.py
azstream/authenticators/bellmedia_external_authenticator/consts.py
azstream/authenticators/bellmedia_external_authenticator/requests.py
azstream/authenticators/jwt_authenticator/__init__.py
azstream/authenticators/jwt_authenticator/jwt_authenticator.py
azstream/authenticators/toutv_authenticator/__init__.py
azstream/authenticators/toutv_authenticator/consts.py
azstream/authenticators/toutv_authenticator/requests.py
azstream/authenticators/toutv_authenticator/toutv_authenticator.py
azstream/authenticators/unauthenticated_authenticator/__init__.py
azstream/authenticators/unauthenticated_authenticator/unauthenticated_authenticator.py
azstream/azstream.py
azstream/platforms/__init__.py
azstream/platforms/authentication_method.py
azstream/platforms/crave/__init__.py
azstream/platforms/crave/crave.py
azstream/platforms/noovo/__init__.py
azstream/platforms/noovo/noovo.py
azstream/platforms/platform/__init__.py
azstream/platforms/platform/platform.py
azstream/platforms/toutv/__init__.py
azstream/platforms/toutv/consts.py
azstream/platforms/toutv/parsers.py
azstream/platforms/toutv/requests.py
azstream/platforms/toutv/toutv.py
azstream/types/__init__.py
azstream/types/search_result.py
azstream/types/title.py
azstream/utils/__init__.py
azstream/utils/formatting.py
azstream/utils/locations.py
azstream-0.1.0.dist-info/LICENSE
azstream-0.1.0.dist-info/METADATA
azstream-0.1.0.dist-info/WHEEL
azstream-0.1.0.dist-info/RECORD
